[
  {
    "ch": "Ch 1 – The Wonderful World of Science",
    "link": "https://drive.google.com/drive/folders/1NncM-qz4ujZv1ID_QwdD1Gm1EaDXGSuC?usp=sharing",
    "status": "available"
  },
  {
    "ch": "Ch 2 – Diversity in the Living World",
    "link": "https://drive.google.com/drive/folders/1yjq29OZ8pc2vTOnZwzMPGIiaUnH9b-Wx?usp=sharing",
    "status": "available"
  },
  {
    "ch": "Ch 3 – Mindful Eating: A Path to Healthy Body",
    "link": "https://drive.google.com/drive/folders/1LIgHB7YLSM_qj8PUKuRgF-xAS-uOd-vO?usp=sharing",
    "status": "available"
  },
  {
    "ch": "Ch 4 – Exploring Magnets",
    "link": "https://drive.google.com/drive/folders/1sWNWuLA2TdffRxdBM4VXBRCvKKwSmBMv?usp=sharing",
    "status": "available"
  },
  {
    "ch": "Ch 5 – Measurement of Length and Motion",
    "link": "https://drive.google.com/drive/folders/1XSMRioorqQ_FhNBiMzCXp05KDB17Upa0?usp=sharing",
    "status": "available"
  },
  {
    "ch": "Ch 6 – Materials Around Us",
    "link": "https://drive.google.com/drive/folders/1nqx1aXf0Vch35l46_hE_e8lwAaOJMZEd?usp=sharing",
    "status": "available"
  },
  {
    "ch": "Ch 7 – Temperature and its Measurement",
    "link": "https://drive.google.com/drive/folders/10Q2CUm29fEdVbJxj0ACAGqlznzdy5ZG_?usp=sharing",
    "status": "available"
  },
  {
    "ch": "Ch 8 – A Journey through States of Water",
    "link": "https://drive.google.com/drive/folders/1YAAyzg81Zq1OYJsqtUmvb3zMjm-F9mCw?usp=sharing",
    "status": "available"
  },
  {
    "ch": "Ch 9 – Methods of Separation in Everyday Life",
    "link": "https://drive.google.com/drive/folders/1rn_UWp4_pqk_CH4grli1fSEiMzfsQd-s?usp=sharing",
    "status": "available"
  },
  {
    "ch": "Ch 10 – Living Creatures: Exploring their Characteristics",
    "link": "https://drive.google.com/drive/folders/1z7zbkIEGAAiGmme2mT6YNoNntg2qTEfN?usp=sharing",
    "status": "available"
  },
  {
    "ch": "Ch 11 – Nature's Treasures",
    "link": "https://drive.google.com/drive/folders/1hvb5nfhJxZTJCOsqSCfGeO926bM0iHg-?usp=sharing",
    "status": "available"
  },
  {
    "ch": "Ch 12 – Beyond Earth",
    "link": "https://drive.google.com/drive/folders/1WFxhdRNfyn_vwhonh7fijhHHo4BcbjdD?usp=sharing",
    "status": "available"
  }
]